robotraconteur_service_browser_gui/RRIcon.bmp
robotraconteur_service_browser_gui/__init__.py
robotraconteur_service_browser_gui/__main__.py
robotraconteur_service_browser_gui/robotraconteur_service_browser_gui.py
robotraconteur_service_browser_gui-0.2.0.dist-info/LICENSE.txt
robotraconteur_service_browser_gui-0.2.0.dist-info/METADATA
robotraconteur_service_browser_gui-0.2.0.dist-info/WHEEL
robotraconteur_service_browser_gui-0.2.0.dist-info/entry_points.txt
robotraconteur_service_browser_gui-0.2.0.dist-info/top_level.txt
robotraconteur_service_browser_gui-0.2.0.dist-info/RECORD
