Metadata-Version: 2.1
Name: robotraconteur-service-browser-gui
Version: 0.2.0
Summary: Robot Raconteur Service Browser GUI
Author-email: John Wason <wason@wasontech.com>
Requires-Python: >=3.6
License-File: LICENSE.txt
Requires-Dist: robotraconteur
Requires-Dist: robotraconteurcompanion
Requires-Dist: PySide6
Requires-Dist: importlib-resources
